[
    {
        "call_number": 1,
        "client_id": 34,
        "E": 0.7301511853636238,
        "temp": 0.02
    },
    {
        "call_number": 2,
        "client_id": 34,
        "E": 0.7558162571692296,
        "temp": 0.0198
    },
    {
        "call_number": 3,
        "client_id": 34,
        "E": 0.7785890407943112,
        "temp": 0.019602
    },
    {
        "call_number": 4,
        "client_id": 34,
        "E": 0.7763820109717194,
        "temp": 0.01940598,
        "count": 1
    },
    {
        "call_number": 5,
        "client_id": 34,
        "E": 0.7824036281179139,
        "temp": 0.0192119202,
        "count": 1
    },
    {
        "call_number": 6,
        "client_id": 34,
        "E": 0.7826704404389493,
        "temp": 0.019019800998,
        "count": 1
    },
    {
        "call_number": 7,
        "client_id": 34,
        "E": 0.7923958856498623,
        "temp": 0.01882960298802,
        "count": 1
    },
    {
        "call_number": 8,
        "client_id": 34,
        "E": 0.8009008476720336,
        "temp": 0.0186413069581398,
        "count": 1
    },
    {
        "call_number": 9,
        "client_id": 34,
        "E": 0.8057617463166695,
        "temp": 0.0184548938885584,
        "count": 1
    },
    {
        "call_number": 10,
        "client_id": 34,
        "E": 0.7972918706717054,
        "temp": 0.018270344949672817,
        "count": 1
    }
]