[
    {
        "call_number": 1,
        "client_id": 54,
        "val_accuracy": 0.6239393939393939,
        "val_f1": 0.6469618464437118,
        "val_fpr": 0.20084268413137688,
        "temp": 0.02,
        "prev_E": 0.6900195187505762,
        "theta": [
            0.0,
            0.0,
            0.0
        ],
        "update": true
    },
    {
        "call_number": 2,
        "client_id": 54,
        "val_accuracy": 0.6309180035650623,
        "val_f1": 0.6511279435822004,
        "val_fpr": 0.1885361143985976,
        "temp": 0.0198,
        "prev_E": 0.6977279327537186,
        "theta": [
            0.000985025253091898,
            0.0006481929194729304,
            -0.0020240727808471027
        ],
        "update": true
    },
    {
        "call_number": 3,
        "client_id": 54,
        "val_accuracy": 0.6870320855614973,
        "val_f1": 0.7056411081178883,
        "val_fpr": 0.18536381352387904,
        "temp": 0.019602,
        "prev_E": 0.7356414677371821,
        "theta": [
            0.0011634881420039915,
            0.0005162040724627367,
            -0.003968855415855576
        ],
        "update": true
    },
    {
        "call_number": 4,
        "client_id": 54,
        "val_accuracy": 0.6990819964349376,
        "val_f1": 0.7190358167539972,
        "val_fpr": 0.18655620712054743,
        "temp": 0.01940598,
        "prev_E": 0.7436989400347207,
        "theta": [
            0.001773986095763145,
            0.0007933184761027239,
            -0.0052614071470848895
        ],
        "update": true
    },
    {
        "call_number": 5,
        "client_id": 54,
        "val_accuracy": 0.7077629233511586,
        "val_f1": 0.7274927654126715,
        "val_fpr": 0.19017343097909753,
        "temp": 0.0192119202,
        "prev_E": 0.7481911447511536,
        "theta": [
            0.002374519305373387,
            0.0010638773037147432,
            -0.006358730474191905
        ],
        "update": true
    },
    {
        "call_number": 6,
        "client_id": 54,
        "val_accuracy": 0.7241176470588235,
        "val_f1": 0.7413538279633461,
        "val_fpr": 0.1703699089687575,
        "temp": 0.019019800998,
        "prev_E": 0.7648210113238822,
        "theta": [
            0.0027770868308456802,
            0.0011780641402182944,
            -0.007708746385724245
        ],
        "update": true
    },
    {
        "call_number": 7,
        "client_id": 54,
        "val_accuracy": 0.7324866310160427,
        "val_f1": 0.7513769053302572,
        "val_fpr": 0.1817065465967841,
        "temp": 0.01882960298802,
        "prev_E": 0.7671940515175371,
        "theta": [
            0.003318162665797475,
            0.0014026751691327845,
            -0.008594207870853838
        ],
        "update": true
    },
    {
        "call_number": 8,
        "client_id": 54,
        "val_accuracy": 0.7358199643493761,
        "val_f1": 0.7530562512692074,
        "val_fpr": 0.16335792274357308,
        "temp": 0.0186413069581398,
        "prev_E": 0.7749111237009089,
        "theta": [
            0.0038434727270902306,
            0.001638937549779961,
            -0.009743237023349569
        ],
        "update": true
    },
    {
        "call_number": 9,
        "client_id": 54,
        "val_accuracy": 0.7241176470588235,
        "val_f1": 0.7416176470588236,
        "val_fpr": 0.17495706493206026,
        "temp": 0.0184548938885584,
        "prev_E": 0.7632989661092106,
        "theta": [
            0.004694483424034462,
            0.00219551910517315,
            -0.010571827319827393
        ],
        "update": false,
        "count": 1
    },
    {
        "call_number": 10,
        "client_id": 54,
        "val_accuracy": 0.734812834224599,
        "val_f1": 0.7517825311942958,
        "val_fpr": 0.16384288879594944,
        "temp": 0.018270344949672817,
        "prev_E": 0.7739227456251876,
        "theta": [
            0.005172061437014868,
            0.0023881134872550808,
            -0.011774808628110946
        ],
        "update": true,
        "count": 1
    }
]