[
    {
        "call_number": 1,
        "client_id": 55,
        "E": 0.722814159094497,
        "temp": 0.02
    },
    {
        "call_number": 2,
        "client_id": 55,
        "E": 0.7429167417195204,
        "temp": 0.0198
    },
    {
        "call_number": 3,
        "client_id": 55,
        "E": 0.7428646289646972,
        "temp": 0.019602
    },
    {
        "call_number": 4,
        "client_id": 55,
        "E": 0.7543936530775999,
        "temp": 0.01940598
    },
    {
        "call_number": 5,
        "client_id": 55,
        "E": 0.7740368621023812,
        "temp": 0.0192119202
    },
    {
        "call_number": 6,
        "client_id": 55,
        "E": 0.7793697153156485,
        "temp": 0.019019800998
    },
    {
        "call_number": 7,
        "client_id": 55,
        "E": 0.7808622904436092,
        "temp": 0.01882960298802
    },
    {
        "call_number": 8,
        "client_id": 55,
        "E": 0.7886859571400537,
        "temp": 0.0186413069581398
    },
    {
        "call_number": 9,
        "client_id": 55,
        "E": 0.7779062818616463,
        "temp": 0.0184548938885584
    },
    {
        "call_number": 10,
        "client_id": 55,
        "E": 0.7832619103536448,
        "temp": 0.018270344949672817
    }
]