[
    {
        "call_number": 1,
        "client_id": 82,
        "E": 0.7155791009512231,
        "temp": 0.02
    },
    {
        "call_number": 2,
        "client_id": 82,
        "E": 0.7473542444531271,
        "temp": 0.0198
    },
    {
        "call_number": 3,
        "client_id": 82,
        "E": 0.7511308225010962,
        "temp": 0.019602
    },
    {
        "call_number": 4,
        "client_id": 82,
        "E": 0.7534952324847184,
        "temp": 0.01940598
    },
    {
        "call_number": 5,
        "client_id": 82,
        "E": 0.7550337748929941,
        "temp": 0.0192119202
    },
    {
        "call_number": 6,
        "client_id": 82,
        "E": 0.7603867370645392,
        "temp": 0.019019800998
    },
    {
        "call_number": 7,
        "client_id": 82,
        "E": 0.7649560330838914,
        "temp": 0.01882960298802
    },
    {
        "call_number": 8,
        "client_id": 82,
        "E": 0.758935130284901,
        "temp": 0.0186413069581398
    },
    {
        "call_number": 9,
        "client_id": 82,
        "E": 0.7688593743350493,
        "temp": 0.0184548938885584
    },
    {
        "call_number": 10,
        "client_id": 82,
        "E": 0.7672815209714816,
        "temp": 0.018270344949672817
    }
]