[
    {
        "call_number": 1,
        "client_id": 42,
        "metrics": {
            "loss": 0.48700001613612764,
            "acc": 0.7572842221000551,
            "f1": 0.7740959282747506,
            "fpr": 0.30633223684210525
        }
    },
    {
        "call_number": 2,
        "client_id": 42,
        "metrics": {
            "loss": 0.33811023232706805,
            "acc": 0.8498075865860363,
            "f1": 0.8565526023111184,
            "fpr": 0.19747807017543859
        }
    },
    {
        "call_number": 3,
        "client_id": 42,
        "metrics": {
            "loss": 0.3012084062815758,
            "acc": 0.862231995601979,
            "f1": 0.8676247502901336,
            "fpr": 0.1805921052631579
        }
    },
    {
        "call_number": 4,
        "client_id": 42,
        "metrics": {
            "loss": 0.2997644196280784,
            "acc": 0.8642111050027488,
            "f1": 0.8704649765616281,
            "fpr": 0.18612938596491227
        }
    },
    {
        "call_number": 5,
        "client_id": 42,
        "metrics": {
            "loss": 0.2683583803493576,
            "acc": 0.8759129820152359,
            "f1": 0.8813109661622021,
            "fpr": 0.17136591478696744
        }
    },
    {
        "call_number": 6,
        "client_id": 42,
        "metrics": {
            "loss": 0.27187395778795087,
            "acc": 0.8725948323254535,
            "f1": 0.8785632341062635,
            "fpr": 0.17872807017543857
        }
    },
    {
        "call_number": 7,
        "client_id": 42,
        "metrics": {
            "loss": 0.25033151861606984,
            "acc": 0.8850100787978743,
            "f1": 0.8902748346662497,
            "fpr": 0.1650219298245614
        }
    },
    {
        "call_number": 8,
        "client_id": 42,
        "metrics": {
            "loss": 0.24623078337669024,
            "acc": 0.8845519516217702,
            "f1": 0.8899774549541694,
            "fpr": 0.16648391812865496
        }
    },
    {
        "call_number": 9,
        "client_id": 42,
        "metrics": {
            "loss": 0.24633529471854368,
            "acc": 0.8793293018141837,
            "f1": 0.8848540620776931,
            "fpr": 0.17077850877192985
        }
    },
    {
        "call_number": 10,
        "client_id": 42,
        "metrics": {
            "loss": 0.24776948834851126,
            "acc": 0.8834524463991204,
            "f1": 0.8882604258794204,
            "fpr": 0.16173245614035087
        }
    }
]