[
    {
        "call_number": 1,
        "client_id": 67,
        "metrics": {
            "loss": 0.8317910536096014,
            "acc": 0.8073569482288828,
            "f1": 0.7940879505093932,
            "fpr": 0.17774158523344194
        }
    },
    {
        "call_number": 2,
        "client_id": 67,
        "metrics": {
            "loss": 0.6654829021671722,
            "acc": 0.851716621253406,
            "f1": 0.8520002517045994,
            "fpr": 0.15841476655808903
        }
    },
    {
        "call_number": 3,
        "client_id": 67,
        "metrics": {
            "loss": 0.6121925027206027,
            "acc": 0.8625068119891008,
            "f1": 0.864888018697215,
            "fpr": 0.16123778501628666
        }
    },
    {
        "call_number": 4,
        "client_id": 67,
        "metrics": {
            "loss": 0.5590290179026538,
            "acc": 0.8789645776566758,
            "f1": 0.8834644245147565,
            "fpr": 0.16297502714440829
        }
    },
    {
        "call_number": 5,
        "client_id": 67,
        "metrics": {
            "loss": 0.5249356240547935,
            "acc": 0.8974386920980926,
            "f1": 0.9018422887411178,
            "fpr": 0.15038002171552664
        }
    },
    {
        "call_number": 6,
        "client_id": 67,
        "metrics": {
            "loss": 0.528537573999372,
            "acc": 0.8873569482288828,
            "f1": 0.8910257572362659,
            "fpr": 0.14940282301845825
        }
    },
    {
        "call_number": 7,
        "client_id": 67,
        "metrics": {
            "loss": 0.484354699223206,
            "acc": 0.9027792915531336,
            "f1": 0.9068863846248248,
            "fpr": 0.14462540716612382
        }
    },
    {
        "call_number": 8,
        "client_id": 67,
        "metrics": {
            "loss": 0.4681479509020674,
            "acc": 0.9109536784741146,
            "f1": 0.9144938639588835,
            "fpr": 0.13333333333333336
        }
    },
    {
        "call_number": 9,
        "client_id": 67,
        "metrics": {
            "loss": 0.4625296388720644,
            "acc": 0.9095912806539509,
            "f1": 0.9130979710378554,
            "fpr": 0.13409337676438657
        }
    },
    {
        "call_number": 10,
        "client_id": 67,
        "metrics": {
            "loss": 0.4820821278953346,
            "acc": 0.9008719346049047,
            "f1": 0.9051326855990409,
            "fpr": 0.14733984799131383
        }
    }
]