[
    {
        "call_number": 1,
        "client_id": 42,
        "metrics": {
            "loss": 0.7847816238277837,
            "acc": 0.8016492578339747,
            "f1": 0.7980891297569377,
            "fpr": 0.20032894736842105
        }
    },
    {
        "call_number": 2,
        "client_id": 42,
        "metrics": {
            "loss": 0.7276387362626562,
            "acc": 0.8126992853216054,
            "f1": 0.8155703657419698,
            "fpr": 0.20625
        }
    },
    {
        "call_number": 3,
        "client_id": 42,
        "metrics": {
            "loss": 0.6455855996985185,
            "acc": 0.8393073117097307,
            "f1": 0.8442032172738976,
            "fpr": 0.1962719298245614
        }
    },
    {
        "call_number": 4,
        "client_id": 42,
        "metrics": {
            "loss": 0.6273223875384583,
            "acc": 0.8419461242440901,
            "f1": 0.8489545853122669,
            "fpr": 0.20745614035087717
        }
    },
    {
        "call_number": 5,
        "client_id": 42,
        "metrics": {
            "loss": 0.5635835359493893,
            "acc": 0.874216602528862,
            "f1": 0.8804126855584637,
            "fpr": 0.17993421052631578
        }
    },
    {
        "call_number": 6,
        "client_id": 42,
        "metrics": {
            "loss": 0.5693288683368449,
            "acc": 0.868719076415613,
            "f1": 0.8740019512806854,
            "fpr": 0.1756578947368421
        }
    },
    {
        "call_number": 7,
        "client_id": 42,
        "metrics": {
            "loss": 0.5491882498327054,
            "acc": 0.8732820230896097,
            "f1": 0.8777644321697101,
            "fpr": 0.1656798245614035
        }
    },
    {
        "call_number": 8,
        "client_id": 42,
        "metrics": {
            "loss": 0.5425949574039695,
            "acc": 0.8711379879054426,
            "f1": 0.876097339440903,
            "fpr": 0.17192982456140352
        }
    },
    {
        "call_number": 9,
        "client_id": 42,
        "metrics": {
            "loss": 0.5289537221193314,
            "acc": 0.8760857614073666,
            "f1": 0.8816689203812345,
            "fpr": 0.1737938596491228
        }
    },
    {
        "call_number": 10,
        "client_id": 42,
        "metrics": {
            "loss": 0.521392456873467,
            "acc": 0.8788894997251235,
            "f1": 0.8843153719545931,
            "fpr": 0.1706140350877193
        }
    }
]