[
    {
        "call_number": 1,
        "client_id": 1,
        "metrics": {
            "loss": 0.600090940884922,
            "acc": 0.8786510136420457,
            "f1": 0.88553141776803,
            "fpr": 0.18058241877648593
        }
    },
    {
        "call_number": 2,
        "client_id": 1,
        "metrics": {
            "loss": 0.5073958902695904,
            "acc": 0.9021414207293874,
            "f1": 0.9061818023697785,
            "fpr": 0.1394327936542432
        }
    },
    {
        "call_number": 3,
        "client_id": 1,
        "metrics": {
            "loss": 0.4705986744748508,
            "acc": 0.9083808902657754,
            "f1": 0.9102027309765,
            "fpr": 0.11201782027599697
        }
    },
    {
        "call_number": 4,
        "client_id": 1,
        "metrics": {
            "loss": 0.43943229401111605,
            "acc": 0.917267242784934,
            "f1": 0.9189292696355285,
            "fpr": 0.10337933282625231
        }
    },
    {
        "call_number": 5,
        "client_id": 1,
        "metrics": {
            "loss": 0.4359020913554274,
            "acc": 0.9169846187292787,
            "f1": 0.9181561046955127,
            "fpr": 0.0976855373247854
        }
    },
    {
        "call_number": 6,
        "client_id": 1,
        "metrics": {
            "loss": 0.4427216242344483,
            "acc": 0.9134246426436219,
            "f1": 0.9145878300558484,
            "fpr": 0.10116266434858198
        }
    },
    {
        "call_number": 7,
        "client_id": 1,
        "metrics": {
            "loss": 0.44060943755507465,
            "acc": 0.9144355671503884,
            "f1": 0.9156295910760776,
            "fpr": 0.0996957513854178
        }
    },
    {
        "call_number": 8,
        "client_id": 1,
        "metrics": {
            "loss": 0.4005993475771469,
            "acc": 0.9280830479917388,
            "f1": 0.9291874834593103,
            "fpr": 0.08789525154840813
        }
    },
    {
        "call_number": 9,
        "client_id": 1,
        "metrics": {
            "loss": 0.39507620911364977,
            "acc": 0.9293113756182402,
            "f1": 0.930343130081807,
            "fpr": 0.08580897533413016
        }
    },
    {
        "call_number": 10,
        "client_id": 1,
        "metrics": {
            "loss": 0.41006671056280963,
            "acc": 0.9231425620957662,
            "f1": 0.9241558929832875,
            "fpr": 0.09050309681625557
        }
    }
]