[
    {
        "call_number": 1,
        "client_id": 56,
        "metrics": {
            "loss": 0.4301606997599204,
            "acc": 0.7972617166929963,
            "f1": 0.8070597389916246,
            "fpr": 0.26403785488959
        }
    },
    {
        "call_number": 2,
        "client_id": 56,
        "metrics": {
            "loss": 0.3169328515852491,
            "acc": 0.8632964718272774,
            "f1": 0.8704704088639319,
            "fpr": 0.19390115667718189
        }
    },
    {
        "call_number": 3,
        "client_id": 56,
        "metrics": {
            "loss": 0.2934203093871474,
            "acc": 0.8765666140073722,
            "f1": 0.8841152488221716,
            "fpr": 0.1903259726603575
        }
    },
    {
        "call_number": 4,
        "client_id": 56,
        "metrics": {
            "loss": 0.27274715423583984,
            "acc": 0.8842548709847289,
            "f1": 0.8920122296273609,
            "fpr": 0.18885383806519454
        }
    },
    {
        "call_number": 5,
        "client_id": 56,
        "metrics": {
            "loss": 0.25930243442455925,
            "acc": 0.8893101632438126,
            "f1": 0.8963142389190322,
            "fpr": 0.17949526813880126
        }
    },
    {
        "call_number": 6,
        "client_id": 56,
        "metrics": {
            "loss": 0.25441417551289003,
            "acc": 0.890585688373998,
            "f1": 0.8978067974582776,
            "fpr": 0.18132959457880593
        }
    },
    {
        "call_number": 7,
        "client_id": 56,
        "metrics": {
            "loss": 0.2501849563999308,
            "acc": 0.8929261014569071,
            "f1": 0.9001182090279594,
            "fpr": 0.18033648790746584
        }
    },
    {
        "call_number": 8,
        "client_id": 56,
        "metrics": {
            "loss": 0.24660392076604898,
            "acc": 0.8949447077409163,
            "f1": 0.9018415565643094,
            "fpr": 0.17648089730108654
        }
    },
    {
        "call_number": 9,
        "client_id": 56,
        "metrics": {
            "loss": 0.22429661441594365,
            "acc": 0.8995787256450765,
            "f1": 0.9062623341953705,
            "fpr": 0.17287066246056784
        }
    },
    {
        "call_number": 10,
        "client_id": 56,
        "metrics": {
            "loss": 0.23563010402851636,
            "acc": 0.8948569422503073,
            "f1": 0.9020088634402135,
            "fpr": 0.17928496319663512
        }
    }
]