[
    {
        "call_number": 1,
        "client_id": 35,
        "metrics": {
            "loss": 0.4067396782970024,
            "acc": 0.81687264911338,
            "f1": 0.8226917039750701,
            "fpr": 0.232762312633833
        }
    },
    {
        "call_number": 2,
        "client_id": 35,
        "metrics": {
            "loss": 0.3318272398076681,
            "acc": 0.8554540569586243,
            "f1": 0.8634916344164398,
            "fpr": 0.20587335576628937
        }
    },
    {
        "call_number": 3,
        "client_id": 35,
        "metrics": {
            "loss": 0.2882598012085941,
            "acc": 0.8752821063944116,
            "f1": 0.8832190700269784,
            "fpr": 0.19486081370449676
        }
    },
    {
        "call_number": 4,
        "client_id": 35,
        "metrics": {
            "loss": 0.27770517565478375,
            "acc": 0.881843692160726,
            "f1": 0.8892047965037059,
            "fpr": 0.1868903164406376
        }
    },
    {
        "call_number": 5,
        "client_id": 35,
        "metrics": {
            "loss": 0.26062084772324157,
            "acc": 0.8898441698011822,
            "f1": 0.8968988998208511,
            "fpr": 0.18118010944563404
        }
    },
    {
        "call_number": 6,
        "client_id": 35,
        "metrics": {
            "loss": 0.260861704319932,
            "acc": 0.8891532969985416,
            "f1": 0.896245035424421,
            "fpr": 0.1818598959926583
        }
    },
    {
        "call_number": 7,
        "client_id": 35,
        "metrics": {
            "loss": 0.23850139588496438,
            "acc": 0.8984416980118215,
            "f1": 0.9039426797610005,
            "fpr": 0.1614561027837259
        }
    },
    {
        "call_number": 8,
        "client_id": 35,
        "metrics": {
            "loss": 0.24200866642634325,
            "acc": 0.8959340856170517,
            "f1": 0.9020885868197658,
            "fpr": 0.1697002141327623
        }
    },
    {
        "call_number": 9,
        "client_id": 35,
        "metrics": {
            "loss": 0.22699099099263548,
            "acc": 0.9019881783987103,
            "f1": 0.9075959184027409,
            "fpr": 0.16167023554603854
        }
    },
    {
        "call_number": 10,
        "client_id": 35,
        "metrics": {
            "loss": 0.22620712488818662,
            "acc": 0.9043524986566361,
            "f1": 0.90952214626498,
            "fpr": 0.15564775160599573
        }
    }
]