[
    {
        "call_number": 1,
        "client_id": 0,
        "metrics": {
            "loss": 0.4391921667060976,
            "acc": 0.7907700709994537,
            "f1": 0.7855861399944531,
            "fpr": 0.2327153762268266
        }
    },
    {
        "call_number": 2,
        "client_id": 0,
        "metrics": {
            "loss": 0.3321724199882612,
            "acc": 0.8588885854724194,
            "f1": 0.8655994257913522,
            "fpr": 0.19261177753544168
        }
    },
    {
        "call_number": 3,
        "client_id": 0,
        "metrics": {
            "loss": 0.30018869467736203,
            "acc": 0.8705018508404638,
            "f1": 0.8781369722947203,
            "fpr": 0.19374772809887314
        }
    },
    {
        "call_number": 4,
        "client_id": 0,
        "metrics": {
            "loss": 0.2707038966360791,
            "acc": 0.8853631895139268,
            "f1": 0.8916101303428767,
            "fpr": 0.17295528898582332
        }
    },
    {
        "call_number": 5,
        "client_id": 0,
        "metrics": {
            "loss": 0.26665290653031193,
            "acc": 0.8882441288913163,
            "f1": 0.895037557727796,
            "fpr": 0.1772082878953108
        }
    },
    {
        "call_number": 6,
        "client_id": 0,
        "metrics": {
            "loss": 0.2478074101281577,
            "acc": 0.8964363735663572,
            "f1": 0.9022839726462557,
            "fpr": 0.16453107960741548
        }
    },
    {
        "call_number": 7,
        "client_id": 0,
        "metrics": {
            "loss": 0.2309663185464411,
            "acc": 0.9020753686510103,
            "f1": 0.9078248980220996,
            "fpr": 0.1612868047982552
        }
    },
    {
        "call_number": 8,
        "client_id": 0,
        "metrics": {
            "loss": 0.23473090063138255,
            "acc": 0.9014746040415073,
            "f1": 0.9072648440228637,
            "fpr": 0.16205016357688112
        }
    },
    {
        "call_number": 9,
        "client_id": 0,
        "metrics": {
            "loss": 0.22087419790402457,
            "acc": 0.9051064991807755,
            "f1": 0.910475500825506,
            "fpr": 0.1559432933478735
        }
    },
    {
        "call_number": 10,
        "client_id": 0,
        "metrics": {
            "loss": 0.2206047332749284,
            "acc": 0.901927128033081,
            "f1": 0.9078226023360012,
            "fpr": 0.163421093628291
        }
    }
]