[
    {
        "call_number": 1,
        "client_id": 53,
        "metrics": {
            "loss": 1.8575651411499294,
            "acc": 0.42687074829931965,
            "f1": 0.3798109989365913,
            "fpr": 0.08321809393908246
        }
    },
    {
        "call_number": 2,
        "client_id": 53,
        "metrics": {
            "loss": 1.467236336214202,
            "acc": 0.5373015873015873,
            "f1": 0.439213057432398,
            "fpr": 0.07152275051846615
        }
    },
    {
        "call_number": 3,
        "client_id": 53,
        "metrics": {
            "loss": 1.3063040488532611,
            "acc": 0.5431972789115647,
            "f1": 0.46630482938938667,
            "fpr": 0.06858810265036995
        }
    },
    {
        "call_number": 4,
        "client_id": 53,
        "metrics": {
            "loss": 1.2361899535570826,
            "acc": 0.5512471655328799,
            "f1": 0.4721052597622536,
            "fpr": 0.06741101605973983
        }
    },
    {
        "call_number": 5,
        "client_id": 53,
        "metrics": {
            "loss": 1.216843429207802,
            "acc": 0.5511337868480726,
            "f1": 0.47910317531023894,
            "fpr": 0.06704030681048082
        }
    },
    {
        "call_number": 6,
        "client_id": 53,
        "metrics": {
            "loss": 1.1666433745196887,
            "acc": 0.5662131519274376,
            "f1": 0.48805326217571887,
            "fpr": 0.0650640109168806
        }
    },
    {
        "call_number": 7,
        "client_id": 53,
        "metrics": {
            "loss": 1.1651241469139957,
            "acc": 0.5607385811467445,
            "f1": 0.48437868600114636,
            "fpr": 0.06603744981533112
        }
    },
    {
        "call_number": 8,
        "client_id": 53,
        "metrics": {
            "loss": 1.1541747261903115,
            "acc": 0.562641723356009,
            "f1": 0.48591989649585754,
            "fpr": 0.06569165100476412
        }
    },
    {
        "call_number": 9,
        "client_id": 53,
        "metrics": {
            "loss": 1.1271831208041738,
            "acc": 0.573469387755102,
            "f1": 0.4968038059199588,
            "fpr": 0.0641630281957529
        }
    },
    {
        "call_number": 10,
        "client_id": 53,
        "metrics": {
            "loss": 1.1043709380818265,
            "acc": 0.5810657596371882,
            "f1": 0.5099471333940709,
            "fpr": 0.06276173869874092
        }
    }
]