[
    {
        "call_number": 1,
        "client_id": 27,
        "metrics": {
            "loss": 1.9691248774528503,
            "acc": 0.3013950073421439,
            "f1": 0.2835044381103315,
            "fpr": 0.09199461532076832
        }
    },
    {
        "call_number": 2,
        "client_id": 27,
        "metrics": {
            "loss": 1.7229348848032395,
            "acc": 0.45433186490455213,
            "f1": 0.4233925508969147,
            "fpr": 0.08069903561687054
        }
    },
    {
        "call_number": 3,
        "client_id": 27,
        "metrics": {
            "loss": 1.6186094572377758,
            "acc": 0.48972099853157125,
            "f1": 0.4532924344592958,
            "fpr": 0.07862114908296873
        }
    },
    {
        "call_number": 4,
        "client_id": 27,
        "metrics": {
            "loss": 1.5491706844448117,
            "acc": 0.513215859030837,
            "f1": 0.48075833117062444,
            "fpr": 0.07499000882969617
        }
    },
    {
        "call_number": 5,
        "client_id": 27,
        "metrics": {
            "loss": 1.5158543874358021,
            "acc": 0.51431718061674,
            "f1": 0.4774034485575618,
            "fpr": 0.074758410734842
        }
    },
    {
        "call_number": 6,
        "client_id": 27,
        "metrics": {
            "loss": 1.5068623221197792,
            "acc": 0.5152716593245228,
            "f1": 0.47455796970581743,
            "fpr": 0.07462259248846506
        }
    },
    {
        "call_number": 7,
        "client_id": 27,
        "metrics": {
            "loss": 1.4976168538248817,
            "acc": 0.5214757709251101,
            "f1": 0.47151761212643306,
            "fpr": 0.073724080492896
        }
    },
    {
        "call_number": 8,
        "client_id": 27,
        "metrics": {
            "loss": 1.4972901195287707,
            "acc": 0.5138582966226138,
            "f1": 0.4554720468343985,
            "fpr": 0.0750474899229815
        }
    },
    {
        "call_number": 9,
        "client_id": 27,
        "metrics": {
            "loss": 1.5224812592184822,
            "acc": 0.512848751835536,
            "f1": 0.45250146785631723,
            "fpr": 0.07536340789652528
        }
    },
    {
        "call_number": 10,
        "client_id": 27,
        "metrics": {
            "loss": 1.5196520110895468,
            "acc": 0.5016519823788546,
            "f1": 0.4353989168207705,
            "fpr": 0.07719662767930029
        }
    }
]