[
    {
        "call_number": 1,
        "client_id": 38,
        "metrics": {
            "loss": 1.8985573530197144,
            "acc": 0.373828125,
            "f1": 0.3448858032345978,
            "fpr": 0.08171524916407906
        }
    },
    {
        "call_number": 2,
        "client_id": 38,
        "metrics": {
            "loss": 1.6596274947126708,
            "acc": 0.4969401041666667,
            "f1": 0.44259522929831957,
            "fpr": 0.06749111642337799
        }
    },
    {
        "call_number": 3,
        "client_id": 38,
        "metrics": {
            "loss": 1.5702960827836285,
            "acc": 0.5190972222222222,
            "f1": 0.4735892407886488,
            "fpr": 0.06410660765152368
        }
    },
    {
        "call_number": 4,
        "client_id": 38,
        "metrics": {
            "loss": 1.5682584447441277,
            "acc": 0.48596643518518523,
            "f1": 0.443542108266776,
            "fpr": 0.06869405358339435
        }
    },
    {
        "call_number": 5,
        "client_id": 38,
        "metrics": {
            "loss": 1.5500828764504855,
            "acc": 0.4991319444444444,
            "f1": 0.4485438988087384,
            "fpr": 0.06729143842563813
        }
    },
    {
        "call_number": 6,
        "client_id": 38,
        "metrics": {
            "loss": 1.5163788370788098,
            "acc": 0.4966145833333333,
            "f1": 0.45055283181762035,
            "fpr": 0.06774381402029014
        }
    },
    {
        "call_number": 7,
        "client_id": 38,
        "metrics": {
            "loss": 1.5192005957166355,
            "acc": 0.4973958333333333,
            "f1": 0.44770507270709126,
            "fpr": 0.06786454447530509
        }
    },
    {
        "call_number": 8,
        "client_id": 38,
        "metrics": {
            "loss": 1.5163191345830758,
            "acc": 0.5000651041666667,
            "f1": 0.45008556211571504,
            "fpr": 0.06754361554157688
        }
    },
    {
        "call_number": 9,
        "client_id": 38,
        "metrics": {
            "loss": 1.5889923885464667,
            "acc": 0.4760416666666667,
            "f1": 0.41622962258600804,
            "fpr": 0.07064745030083679
        }
    },
    {
        "call_number": 10,
        "client_id": 38,
        "metrics": {
            "loss": 1.5230047394831978,
            "acc": 0.4985026041666667,
            "f1": 0.4460635238759658,
            "fpr": 0.06789900911881766
        }
    }
]