[
    {
        "call_number": 1,
        "client_id": 54,
        "metrics": {
            "loss": 1.963549081749386,
            "acc": 0.2919914953933381,
            "f1": 0.2323625246936143,
            "fpr": 0.09444310525092496
        }
    },
    {
        "call_number": 2,
        "client_id": 54,
        "metrics": {
            "loss": 1.7254448159535727,
            "acc": 0.44613749114103474,
            "f1": 0.3784298646050318,
            "fpr": 0.08231091645298841
        }
    },
    {
        "call_number": 3,
        "client_id": 54,
        "metrics": {
            "loss": 1.5900005176332261,
            "acc": 0.4916371367824238,
            "f1": 0.45027046138420923,
            "fpr": 0.07612508249838
        }
    },
    {
        "call_number": 4,
        "client_id": 54,
        "metrics": {
            "loss": 1.5815288972854613,
            "acc": 0.48703047484053863,
            "f1": 0.45065958428678554,
            "fpr": 0.0767322769791138
        }
    },
    {
        "call_number": 5,
        "client_id": 54,
        "metrics": {
            "loss": 1.4815381765365598,
            "acc": 0.5215450035435861,
            "f1": 0.4898809972685513,
            "fpr": 0.0729071809440254
        }
    },
    {
        "call_number": 6,
        "client_id": 54,
        "metrics": {
            "loss": 1.4859481101648677,
            "acc": 0.5111622962437987,
            "f1": 0.47029640641635134,
            "fpr": 0.07437633611758744
        }
    },
    {
        "call_number": 7,
        "client_id": 54,
        "metrics": {
            "loss": 1.4949526076846653,
            "acc": 0.5051736357193479,
            "f1": 0.45605645152011504,
            "fpr": 0.07542089178091196
        }
    },
    {
        "call_number": 8,
        "client_id": 54,
        "metrics": {
            "loss": 1.506068318155077,
            "acc": 0.5033309709425938,
            "f1": 0.4437222979057622,
            "fpr": 0.07579251046151178
        }
    },
    {
        "call_number": 9,
        "client_id": 54,
        "metrics": {
            "loss": 1.4587991972764334,
            "acc": 0.5101878100637846,
            "f1": 0.4437604627222153,
            "fpr": 0.07509538658059547
        }
    },
    {
        "call_number": 10,
        "client_id": 54,
        "metrics": {
            "loss": 1.4766184175456012,
            "acc": 0.5059059768485706,
            "f1": 0.437639111442367,
            "fpr": 0.07611012444520429
        }
    }
]