[
    {
        "call_number": 1,
        "client_id": 0,
        "metrics": {
            "loss": 1.9563248349061566,
            "acc": 0.3961340042035539,
            "f1": 0.3885044988395497,
            "fpr": 0.07480914897755642
        }
    },
    {
        "call_number": 2,
        "client_id": 0,
        "metrics": {
            "loss": 1.643257994685785,
            "acc": 0.4512451436214254,
            "f1": 0.39434495510175155,
            "fpr": 0.07250864406527038
        }
    },
    {
        "call_number": 3,
        "client_id": 0,
        "metrics": {
            "loss": 1.4720236010561165,
            "acc": 0.5225909177759377,
            "f1": 0.47000573761694253,
            "fpr": 0.062211610776850265
        }
    },
    {
        "call_number": 4,
        "client_id": 0,
        "metrics": {
            "loss": 1.383186871323226,
            "acc": 0.5488503916947965,
            "f1": 0.49494451126307437,
            "fpr": 0.058422599622529034
        }
    },
    {
        "call_number": 5,
        "client_id": 0,
        "metrics": {
            "loss": 1.343009938169157,
            "acc": 0.5559245543959893,
            "f1": 0.5006469001589037,
            "fpr": 0.057683598747833124
        }
    },
    {
        "call_number": 6,
        "client_id": 0,
        "metrics": {
            "loss": 1.3016740599499215,
            "acc": 0.5635946754983758,
            "f1": 0.5057580458368458,
            "fpr": 0.05700355085305599
        }
    },
    {
        "call_number": 7,
        "client_id": 0,
        "metrics": {
            "loss": 1.2705005491823869,
            "acc": 0.5697089357365773,
            "f1": 0.5097300531835486,
            "fpr": 0.05644862323628176
        }
    },
    {
        "call_number": 8,
        "client_id": 0,
        "metrics": {
            "loss": 1.2486797573852928,
            "acc": 0.5743264760206355,
            "f1": 0.5141734987044443,
            "fpr": 0.05590722735056145
        }
    },
    {
        "call_number": 9,
        "client_id": 0,
        "metrics": {
            "loss": 1.2508033371263028,
            "acc": 0.5724730908859308,
            "f1": 0.512019469376831,
            "fpr": 0.05622913356308705
        }
    },
    {
        "call_number": 10,
        "client_id": 0,
        "metrics": {
            "loss": 1.2273018369728095,
            "acc": 0.5797210368766321,
            "f1": 0.5187485434212731,
            "fpr": 0.055325418793913325
        }
    }
]