[
    {
        "call_number": 1,
        "client_id": 3,
        "metrics": {
            "train_loss": 0.13481558859348297,
            "train_accuracy": 0.815507216063585,
            "train_precision": 0.8006680005420529,
            "train_recall": 0.8402459427806592,
            "train_f1": 0.819979672556727,
            "train_fpr": 0.20923772069282906
        }
    },
    {
        "call_number": 2,
        "client_id": 3,
        "metrics": {
            "train_loss": 0.9899278879165649,
            "train_accuracy": 0.8134490692323781,
            "train_precision": 0.7964338546487252,
            "train_recall": 0.8422118119457922,
            "train_f1": 0.8186833962862522,
            "train_fpr": 0.21532089364906704
        }
    },
    {
        "call_number": 3,
        "client_id": 3,
        "metrics": {
            "train_loss": 3.0391757488250732,
            "train_accuracy": 0.8146245555323154,
            "train_precision": 0.7967260965604291,
            "train_recall": 0.8448469131671407,
            "train_f1": 0.8200812017864393,
            "train_fpr": 0.21560538867040416
        }
    }
]