[
    {
        "call_number": 1,
        "client_id": 37,
        "metrics": {
            "loss": 0.8207947324713072,
            "acc": 0.8185751978891819,
            "f1": 0.8248201278661333,
            "fpr": 0.2158061116965227
        }
    },
    {
        "call_number": 2,
        "client_id": 37,
        "metrics": {
            "loss": 0.7331845209499199,
            "acc": 0.8343535620052771,
            "f1": 0.833701309523564,
            "fpr": 0.16617492096944153
        }
    },
    {
        "call_number": 3,
        "client_id": 37,
        "metrics": {
            "loss": 0.6547758071621258,
            "acc": 0.8686543535620052,
            "f1": 0.8682958271759643,
            "fpr": 0.1380400421496312
        }
    },
    {
        "call_number": 4,
        "client_id": 37,
        "metrics": {
            "loss": 0.561556068956852,
            "acc": 0.8989973614775725,
            "f1": 0.9021985793997956,
            "fpr": 0.1357218124341412
        }
    },
    {
        "call_number": 5,
        "client_id": 37,
        "metrics": {
            "loss": 0.5500727171202501,
            "acc": 0.8970448548812664,
            "f1": 0.8998265206336544,
            "fpr": 0.13329820864067438
        }
    },
    {
        "call_number": 6,
        "client_id": 37,
        "metrics": {
            "loss": 0.5188253413140773,
            "acc": 0.9096569920844326,
            "f1": 0.9139319686268671,
            "fpr": 0.14151738672286618
        }
    },
    {
        "call_number": 7,
        "client_id": 37,
        "metrics": {
            "loss": 0.526412341495355,
            "acc": 0.9009894459102903,
            "f1": 0.9048975448775038,
            "fpr": 0.14159641728134878
        }
    },
    {
        "call_number": 8,
        "client_id": 37,
        "metrics": {
            "loss": 0.4984294719994069,
            "acc": 0.9122955145118732,
            "f1": 0.9163331922272049,
            "fpr": 0.13730242360379347
        }
    },
    {
        "call_number": 9,
        "client_id": 37,
        "metrics": {
            "loss": 0.48585573881864547,
            "acc": 0.9173614775725593,
            "f1": 0.9215868880660869,
            "fpr": 0.13782929399367755
        }
    },
    {
        "call_number": 10,
        "client_id": 37,
        "metrics": {
            "loss": 0.49179569194093353,
            "acc": 0.9150395778364117,
            "f1": 0.9189978666748663,
            "fpr": 0.1352739726027397
        }
    }
]